[
  {
    "full_name": "feder-cr/Jobs_Applier_AI_Agent_AIHawk",
    "stargazers_count": 26990,
    "open_issues_count": 20,
    "forks_count": 4003
  },
  {
    "full_name": "Stability-AI/stablediffusion",
    "stargazers_count": 39972,
    "open_issues_count": 295,
    "forks_count": 5131
  },
  {
    "full_name": "XingangPan/DragGAN",
    "stargazers_count": 35844,
    "open_issues_count": 153,
    "forks_count": 3458
  },
  {
    "full_name": "thecodeholic/laravel-vue-ecommerce",
    "stargazers_count": 660,
    "open_issues_count": 15,
    "forks_count": 198
  },
  {
    "full_name": "SebLague/Geographical-Adventures",
    "stargazers_count": 3495,
    "open_issues_count": 41,
    "forks_count": 508
  },
  {
    "full_name": "akaunting/akaunting",
    "stargazers_count": 8338,
    "open_issues_count": 9,
    "forks_count": 2517
  },
  {
    "full_name": "teja156/swiggy-total-spent",
    "stargazers_count": 19,
    "open_issues_count": 1,
    "forks_count": 12
  },
  {
    "full_name": "bradtraversy/website-accessibility-tester",
    "stargazers_count": 64,
    "open_issues_count": 1,
    "forks_count": 25
  },
  {
    "full_name": "angular/angular.js",
    "stargazers_count": 58772,
    "open_issues_count": 463,
    "forks_count": 27447
  },
  {
    "full_name": "ossu/computer-science",
    "stargazers_count": 175112,
    "open_issues_count": 16,
    "forks_count": 22195
  },
  {
    "full_name": "shivaamm/Coding-Practice",
    "stargazers_count": 41,
    "open_issues_count": 0,
    "forks_count": 11
  },
  {
    "full_name": "bcit-ci/CodeIgniter",
    "stargazers_count": 18260,
    "open_issues_count": 97,
    "forks_count": 7597
  },
  {
    "full_name": "rachitiitr/modern-cpp-tricks",
    "stargazers_count": 704,
    "open_issues_count": 2,
    "forks_count": 62
  },
  {
    "full_name": "extrawurst/gitui",
    "stargazers_count": 19071,
    "open_issues_count": 225,
    "forks_count": 589
  },
  {
    "full_name": "adityashinde521/DataShield",
    "stargazers_count": 5,
    "open_issues_count": 0,
    "forks_count": 5
  },
  {
    "full_name": "leonardomso/33-js-concepts",
    "stargazers_count": 64526,
    "open_issues_count": 83,
    "forks_count": 9026
  },
  {
    "full_name": "microsoft/Web-Dev-For-Beginners",
    "stargazers_count": 84721,
    "open_issues_count": 116,
    "forks_count": 12589
  },
  {
    "full_name": "techvraksh/roadmap-web-development",
    "stargazers_count": 13,
    "open_issues_count": 0,
    "forks_count": 0
  },
  {
    "full_name": "cfenollosa/os-tutorial",
    "stargazers_count": 27770,
    "open_issues_count": 122,
    "forks_count": 3342
  },
  {
    "full_name": "codecrafters-io/build-your-own-x",
    "stargazers_count": 330097,
    "open_issues_count": 353,
    "forks_count": 30574
  },
  {
    "full_name": "bradtraversy/design-resources-for-developers",
    "stargazers_count": 59782,
    "open_issues_count": 0,
    "forks_count": 11613
  }
]