[
  {
    "full_name": "feder-cr/Jobs_Applier_AI_Agent_AIHawk",
    "stargazers_count": 28161,
    "open_issues_count": 11,
    "forks_count": 4219
  },
  {
    "full_name": "Stability-AI/stablediffusion",
    "stargazers_count": 40988,
    "open_issues_count": 301,
    "forks_count": 5247
  },
  {
    "full_name": "XingangPan/DragGAN",
    "stargazers_count": 35916,
    "open_issues_count": 153,
    "forks_count": 3448
  },
  {
    "full_name": "thecodeholic/laravel-vue-ecommerce",
    "stargazers_count": 678,
    "open_issues_count": 15,
    "forks_count": 207
  },
  {
    "full_name": "SebLague/Geographical-Adventures",
    "stargazers_count": 3542,
    "open_issues_count": 41,
    "forks_count": 517
  },
  {
    "full_name": "akaunting/akaunting",
    "stargazers_count": 8617,
    "open_issues_count": 6,
    "forks_count": 2591
  },
  {
    "full_name": "teja156/swiggy-total-spent",
    "stargazers_count": 20,
    "open_issues_count": 1,
    "forks_count": 12
  },
  {
    "full_name": "bradtraversy/website-accessibility-tester",
    "stargazers_count": 64,
    "open_issues_count": 1,
    "forks_count": 25
  },
  {
    "full_name": "angular/angular.js",
    "stargazers_count": 58743,
    "open_issues_count": 463,
    "forks_count": 27387
  },
  {
    "full_name": "ossu/computer-science",
    "stargazers_count": 179916,
    "open_issues_count": 14,
    "forks_count": 22828
  },
  {
    "full_name": "shivaamm/Coding-Practice",
    "stargazers_count": 41,
    "open_issues_count": 0,
    "forks_count": 11
  },
  {
    "full_name": "bcit-ci/CodeIgniter",
    "stargazers_count": 18252,
    "open_issues_count": 103,
    "forks_count": 7660
  },
  {
    "full_name": "rachitiitr/modern-cpp-tricks",
    "stargazers_count": 708,
    "open_issues_count": 2,
    "forks_count": 62
  },
  {
    "full_name": "gitui-org/gitui",
    "stargazers_count": 19578,
    "open_issues_count": 229,
    "forks_count": 610
  },
  {
    "full_name": "adityashinde521/DataShield",
    "stargazers_count": 5,
    "open_issues_count": 0,
    "forks_count": 5
  },
  {
    "full_name": "leonardomso/33-js-concepts",
    "stargazers_count": 65163,
    "open_issues_count": 82,
    "forks_count": 9102
  },
  {
    "full_name": "microsoft/Web-Dev-For-Beginners",
    "stargazers_count": 88047,
    "open_issues_count": 144,
    "forks_count": 13308
  },
  {
    "full_name": "techvraksh/roadmap-web-development",
    "stargazers_count": 13,
    "open_issues_count": 0,
    "forks_count": 0
  },
  {
    "full_name": "cfenollosa/os-tutorial",
    "stargazers_count": 28290,
    "open_issues_count": 123,
    "forks_count": 3390
  },
  {
    "full_name": "codecrafters-io/build-your-own-x",
    "stargazers_count": 380523,
    "open_issues_count": 383,
    "forks_count": 35434
  },
  {
    "full_name": "bradtraversy/design-resources-for-developers",
    "stargazers_count": 61189,
    "open_issues_count": 1,
    "forks_count": 11736
  }
]